odoo/addons/product_import/README.rst
odoo/addons/product_import/__init__.py
odoo/addons/product_import/__manifest__.py
odoo/addons/product_import/i18n/es.po
odoo/addons/product_import/i18n/product_import.pot
odoo/addons/product_import/readme/CONTRIBUTORS.rst
odoo/addons/product_import/readme/DESCRIPTION.rst
odoo/addons/product_import/security/ir.model.access.csv
odoo/addons/product_import/static/description/icon.png
odoo/addons/product_import/static/description/index.html
odoo/addons/product_import/tests/__init__.py
odoo/addons/product_import/tests/common.py
odoo/addons/product_import/tests/test_parse_validate.py
odoo/addons/product_import/tests/test_product_import.py
odoo/addons/product_import/wizard/__init__.py
odoo/addons/product_import/wizard/product_import.py
odoo/addons/product_import/wizard/product_import_view.xml
odoo14_addon_product_import-14.0.1.3.0.dist-info/METADATA
odoo14_addon_product_import-14.0.1.3.0.dist-info/WHEEL
odoo14_addon_product_import-14.0.1.3.0.dist-info/top_level.txt
odoo14_addon_product_import-14.0.1.3.0.dist-info/RECORD
